ddc459050edb75a05942__mypyc.cpython-313-darwin.so
tomli-2.4.0.dist-info/RECORD
tomli-2.4.0.dist-info/WHEEL
tomli-2.4.0.dist-info/top_level.txt
tomli-2.4.0.dist-info/METADATA
tomli-2.4.0.dist-info/licenses/LICENSE
tomli/_types.py
tomli/_re.cpython-313-darwin.so
tomli/__init__.cpython-313-darwin.so
tomli/__init__.py
tomli/_types.cpython-313-darwin.so
tomli/_parser.py
tomli/_re.py
tomli/py.typed
tomli/_parser.cpython-313-darwin.so
