Metadata-Version: 2.4
Name: tomli
Version: 2.4.0
Summary: A lil' TOML parser
Author-email: Taneli Hukkinen <hukkin@users.noreply.github.com>
License-Expression: MIT
Project-URL: Homepage, https://github.com/hukkin/tomli
Project-URL: Changelog, https://github.com/hukkin/tomli/blob/master/CHANGELOG.md
Keywords: toml
Classifier: Operating System :: MacOS
Classifier: Operating System :: Microsoft :: Windows
Classifier: Operating System :: POSIX :: Linux
Classifier: Programming Language :: Python :: 3 :: Only
Classifier: Programming Language :: Python :: Implementation :: CPython
Classifier: Programming Language :: Python :: Implementation :: PyPy
Classifier: Topic :: Software Development :: Libraries :: Python Modules
Classifier: Typing :: Typed
Requires-Python: >=3.8
License-File: LICENSE
Dynamic: license-file
